streamlit_select_image/__init__.py
streamlit_select_image/frontend/build/asset-manifest.json
streamlit_select_image/frontend/build/bootstrap.min.css
streamlit_select_image/frontend/build/index.html
streamlit_select_image/frontend/build/precache-manifest.4781d6d02f88bd554eb8aef26c0ca8ec.js
streamlit_select_image/frontend/build/service-worker.js
streamlit_select_image/frontend/build/static/js/2.f0f20907.chunk.js
streamlit_select_image/frontend/build/static/js/2.f0f20907.chunk.js.LICENSE.txt
streamlit_select_image/frontend/build/static/js/2.f0f20907.chunk.js.map
streamlit_select_image/frontend/build/static/js/main.018c1d8c.chunk.js
streamlit_select_image/frontend/build/static/js/main.018c1d8c.chunk.js.map
streamlit_select_image/frontend/build/static/js/runtime-main.182a64f4.js
streamlit_select_image/frontend/build/static/js/runtime-main.182a64f4.js.map
streamlit_streamlit_select_image-0.0.1.dist-info/LICENSE
streamlit_streamlit_select_image-0.0.1.dist-info/METADATA
streamlit_streamlit_select_image-0.0.1.dist-info/WHEEL
streamlit_streamlit_select_image-0.0.1.dist-info/top_level.txt
streamlit_streamlit_select_image-0.0.1.dist-info/RECORD
